{
    "id": "BaaBaaBlackSheep",
    "name":"Baa Baa Black Sheep",
    "banner":"//www.storynory.com/wp-content/uploads/2018/11/7C2A7034-D6B1-4C70-B5CB-1B2F1606A9DC.jpeg",
    "audio":"//omny.fm/shows/storynory/song-ba-ba-black-sheep.mp3",
    "by":"Sung by Jana for Storynory",
    "story":["Baa Baa black sheep,",
        "Have you any wool?",
        "Yes sir, yes sir",
        "Three bags full..",
        "",
        "One for the master",
        "And one for the dame,",
        "One for the little boy who lives down the lane.",
        "",
        "Baa baa black sheep,",
        "Have you any wool?",
        "Yes sir, yes sir,",
        "Three bags full."]
}